{
  "collection_base_name": "red_hat_build_of_microshift",
  "collection_full_name": "Red Hat build of MicroShift",
  "common_sources": [],
  "versions": [
    {
      "version_number": "4.18",
      "store_directive": "create_or_keep",
      "sources": [
        {
          "ingestion_type": "redhat_doc",
          "language": "en-US"
        }
      ]
    },
    {
      "version_number": "4.17",
      "store_directive": "create_or_keep",
      "sources": [
        {
          "ingestion_type": "redhat_doc",
          "language": "en-US"
        }
      ]
    },
    {
      "version_number": "4.16",
      "store_directive": "delete",
      "sources": [
        {
          "ingestion_type": "redhat_doc",
          "language": "en-US"
        }
      ]
    },
    {
      "version_number": "4.15",
      "store_directive": "delete",
      "sources": [
        {
          "ingestion_type": "redhat_doc",
          "language": "en-US"
        }
      ]
    },
    {
      "version_number": "4.14",
      "store_directive": "delete",
      "sources": [
        {
          "ingestion_type": "redhat_doc",
          "language": "en-US"
        }
      ]
    },
    {
      "version_number": "4.13",
      "store_directive": "delete",
      "sources": [
        {
          "ingestion_type": "redhat_doc",
          "language": "en-US"
        }
      ]
    },
    {
      "version_number": "4.12",
      "store_directive": "delete",
      "sources": [
        {
          "ingestion_type": "redhat_doc",
          "language": "en-US"
        }
      ]
    }
  ]
}